{"FL-ANNABELLE-9K":{"id":"93709794","name":"FL-ANNABELLE-9K","colorObject":{"BLACK":[999],"DUSTY PINK":[999],"TAN":[999],"TAUPE":[999]},"runObject":{"FL-E18":[999,999,999,999]}},"FL-ARIANA-38":{"id":"93608220","name":"FL-ARIANA-38","colorObject":{"BLACK":[0,0],"TAN":[999,999],"TAUPE":[999,999]},"runObject":{"FL-A12":[0,999,999],"FL-B12":[0,999,999]}},"FL-ATLANTIC-06":{"id":"93114795","name":"FL-ATLANTIC-06","colorObject":{"BLACK":[999],"BROWN":[999,999],"TAN":[999,999],"WHITE":[0]},"runObject":{"FL-A12":[999,999,999,0],"FL-B12":[999,999]}},"FL-AURA-12":{"id":"92667801","name":"FL-AURA-12","colorObject":{"BLACK":[999,0],"TAN":[999,999]},"runObject":{"FL-A12":[999,999],"FL-B12":[0,999]}},"FL-AVA-05K":{"id":"93508869","name":"FL-AVA-05K","colorObject":{"ORANGE":[999],"PINK":[0],"RED":[999],"YELLOW":[999]},"runObject":{"FL-E18":[999,0,999,999]}},"FL-BERK-24K":{"id":"93310511","name":"FL-BERK-24K","colorObject":{"BLACK":[999],"FUCHSIA":[999],"MAUVE":[999],"PINK TIE DYE":[999],"TAN":[0]},"runObject":{"FL-E18":[999,999,999,999,0]}},"FL-BONUS-22":{"id":"93785006","name":"FL-BONUS-22","colorObject":{"BLACK":[999,999],"CHAMPAGNE":[999,0],"SILVER":[999,999]},"runObject":{"FL-A18":[999,999,999],"FL-B18":[999,0,999]}},"FL-BRAIDED-69":{"id":"93355682","name":"FL-BRAIDED-69","colorObject":{"BLACK":[999],"NUDE":[999,0]},"runObject":{"FL-A18":[999,999],"FL-B18":[0]}},"FL-BRAVE-12K":{"id":"93687595","name":"FL-BRAVE-12K","colorObject":{"BLACK":[0],"RED":[0]},"runObject":{"FL-E18":[0,0]}},"FL-CAMILA-69":{"id":"91609226","name":"FL-CAMILA-69","colorObject":{"BLACK":[999,999],"BROWN":[999,999],"TAN":[0,0]},"runObject":{"FL-A18":[999,999,0],"FL-B18":[999,999,0]}},"FL-CBC-76K":{"id":"92247640","name":"FL-CBC-76K","colorObject":{"BLACK":[999],"TAUPE":[999],"WHITE":[999]},"runObject":{"FL-E18":[999,999,999]}},"FL-CHIEF-63":{"id":"93491716","name":"FL-CHIEF-63","colorObject":{"BLACK PATENT":[999,0],"BLACK PU":[999],"WHITE PATENT":[999,999],"WINE PATENT":[999]},"runObject":{"FL-A18":[999,999],"FL-B18":[0,999,999,999]}},"FL-CLOSELY-1":{"id":"93424313","name":"FL-CLOSELY-1","colorObject":{"NUDE":[0]},"runObject":{"FL-A18":[0]}},"FL-CONSTANT-9":{"id":"93101141","name":"FL-CONSTANT-9","colorObject":{"BLACK":[999,999],"WHITE":[999,0]},"runObject":{"FL-A18":[999,999],"FL-B18":[999,0]}},"FL-CUBE-07":{"id":"93944140","name":"FL-CUBE-07","colorObject":{"BLACK":[999,999],"SILVER":[999,999],"TAUPE":[999,999]},"runObject":{"FL-A18":[999,999,999],"FL-B18":[999,999,999]}},"FL-DAISO-18":{"id":"93310673","name":"FL-DAISO-18","colorObject":{"BLACK":[0,0],"CHAMPAGNE":[999,999],"ROSE GOLD":[999,999],"SILVER":[999,999]},"runObject":{"FL-A18":[0,999,999,999],"FL-B18":[0,999,999,999]}},"FL-DANIELLE-76":{"id":"92958076","name":"FL-DANIELLE-76","colorObject":{"BLACK PATENT":[0],"BLUSH":[999,999],"RED":[999]},"runObject":{"FL-A18":[0,999,999],"FL-B18":[999]}},"FL-DASIA-H1":{"id":"91611577","name":"FL-DASIA-H1","colorObject":{"BLACK":[999,0],"BROWN":[999,999],"GREY":[999,999],"RED":[999,999],"TAN":[999,999],"TAUPE":[999,999],"WINE":[999,999]},"runObject":{"FL-A12":[999,999,999,999,999,999,999],"FL-B12":[0,999,999,999,999,999,999]}},"FL-DORIS-59":{"id":"93319991","name":"FL-DORIS-59","colorObject":{"BLACK":[0,0],"CHAMPAGNE":[999,999],"SILVER":[999,999]},"runObject":{"FL-A18":[0,999,999],"FL-B18":[0,999,999]}},"FL-DORIT-69":{"id":"92683780","name":"FL-DORIT-69","colorObject":{"BLACK":[999],"RED":[999,999],"TAN":[0],"TAUPE":[999]},"runObject":{"FL-A18":[999,999,0,999],"FL-B18":[999]}},"FL-ENRICH-18":{"id":"93692740","name":"FL-ENRICH-18","colorObject":{"TAN":[999]},"runObject":{"FL-B18":[999]}},"FL-ERITA-19":{"id":"92169358","name":"FL-ERITA-19","colorObject":{"BLUSH":[999],"MUSTARD":[999],"RED":[999]},"runObject":{"FL-A18":[999,999,999]}},"FL-ERITA-77":{"id":"93136012","name":"FL-ERITA-77","colorObject":{"BLACK":[999,999],"TAN":[999],"TAUPE":[999,0],"WHITE":[999,999]},"runObject":{"FL-A18":[999,999,999,999],"FL-B18":[999,0,999]}},"FL-EVENT-94":{"id":"93620744","name":"FL-EVENT-94","colorObject":{"BLUE":[999],"RED":[999],"SILVER":[999,0]},"runObject":{"FL-A18":[999,999,999],"FL-B18":[0]}},"FL-FANNIE-101":{"id":"93335886","name":"FL-FANNIE-101","colorObject":{"BLACK":[999,999],"RAINBOW":[999,999],"RED":[999,999],"WHITE":[999,999]},"runObject":{"FL-A18":[999,999,999,999],"FL-B18":[999,999,999,999]}},"FL-FISHER-50K":{"id":"93356958","name":"FL-FISHER-50K","colorObject":{"BLACK":[999],"CHAMPAGNE":[999],"ROSE GOLD":[999],"SILVER":[999]},"runObject":{"FL-E18":[999,999,999,999]}},"FL-FISHER-7":{"id":"93696984","name":"FL-FISHER-7","colorObject":{"BEIGE":[0,999],"RED":[999],"WHITE":[999]},"runObject":{"FL-A18":[0,999,999],"FL-B18":[999]}},"FL-FISHER-8":{"id":"93198767","name":"FL-FISHER-8","colorObject":{"BLACK":[999],"CHAMPAGNE":[999],"RED":[999,0],"YELLOW":[999,999]},"runObject":{"FL-A18":[999,999,999],"FL-B18":[999,0,999]}},"FL-FISHER-9":{"id":"93356992","name":"FL-FISHER-9","colorObject":{"BEIGE":[999,999],"BLACK":[999,0],"TAN":[999,999]},"runObject":{"FL-A18":[999,999,999],"FL-B18":[999,0,999]}},"FL-FLEXIBLE-23K":{"id":"93198791","name":"FL-FLEXIBLE-23K","colorObject":{"BLACK":[999],"DUSTY PINK":[999],"FUCHSIA":[999],"TAN":[999]},"runObject":{"FL-E18":[999,999,999,999]}},"FL-FLEXIBLE-24K":{"id":"93198803","name":"FL-FLEXIBLE-24K","colorObject":{"BEIGE":[999],"BLACK":[999],"PINK":[999],"RED":[999],"WHITE":[999]},"runObject":{"FL-E18":[999,999,999,999,999]}},"FL-FLEXIBLE-32K":{"id":"92114282","name":"FL-FLEXIBLE-32K","colorObject":{"BEIGE":[999],"BLACK":[999],"PINK":[999],"TAN":[999]},"runObject":{"FL-E18":[999,999,999,999]}},"FL-FLEXIBLE-49KA":{"id":"93202970","name":"FL-FLEXIBLE-49KA","colorObject":{"BEIGE":[999],"BLACK":[999],"PINK":[999],"WHITE":[999]},"runObject":{"FL-DD":[999,999,999,999]}},"FL-FLEXIBLE-52K":{"id":"92920501","name":"FL-FLEXIBLE-52K","colorObject":{"BLACK":[999],"DUSTY PINK":[999],"RED":[999]},"runObject":{"FL-E18":[999,999,999]}},"FL-FLEXIBLE-53K":{"id":"92920508","name":"FL-FLEXIBLE-53K","colorObject":{"BLACK":[999],"DUSTY PINK":[999]},"runObject":{"FL-E18":[999,999]}},"FL-FLOW-19":{"id":"92172828","name":"FL-FLOW-19","colorObject":{"BLACK":[0],"BLACK MULTI":[999,999],"BLACK CLEAR":[999,999],"HOT PINK TIE DYE":[999,999],"LIGHT BLUE":[999,0],"LAVENDER":[999,999],"MAUVE":[999],"MULTI":[999,999],"OLIVE":[999],"ORANGE TIE DYE":[999],"PINK":[999,999],"PURPLE TIE DYE":[999,999],"RED TIE DYE":[999],"RED":[999],"ROSE TIE DYE":[999,999],"SILVER GREY":[999,999],"WHITE":[0]},"runObject":{"FL-B18":[0,999,999,999,0,999,999,999,999,999,999,999,999],"FL-A18":[999,999,999,999,999,999,999,999,999,999,999,999,999,0]}},"FL-FLOW-19K":{"id":"92517708","name":"FL-FLOW-19K","colorObject":{"BEIGE":[999],"BLACK":[999],"BLACK CLEAR":[999],"BURGUNDY":[999],"FUCHSIA":[999],"LIGHT BLUE":[999],"LAVENDER":[999],"MAUVE":[999],"PINK":[999],"PURPLE":[999],"RED TIE DYE":[999],"RED":[999],"ROSE TIE DYE":[999],"SILVER GREY":[999],"WHITE":[999]},"runObject":{"FL-E18":[999,999,999,999,999,999,999,999,999,999,999,999,999,999,999]}},"FL-FOCUS-33":{"id":"92669594","name":"FL-FOCUS-33","colorObject":{"BLACK":[999],"RED":[999],"TAN":[999],"WHITE":[999,999]},"runObject":{"FL-L12":[999,999],"FL-B12":[999,999],"FL-A12":[999]}},"FL-FORMAT-13":{"id":"94240632","name":"FL-FORMAT-13","colorObject":{"BLACK":[999],"MAUVE":[999],"RED":[999],"WHITE":[999,999]},"runObject":{"FL-B18":[999,999,999,999],"FL-A18":[999]}},"FL-FREEDOM-16":{"id":"93725155","name":"FL-FREEDOM-16","colorObject":{"BLACK":[0],"TAN":[999],"TAUPE":[999,999]},"runObject":{"FL-B18":[0,999,999],"FL-A18":[999]}},"FL-GABBY-67":{"id":"93357070","name":"FL-GABBY-67","colorObject":{"BLACK":[999],"FUCHSIA":[999,999],"PINK":[0,999],"WHITE":[0,999],"YELLOW":[999,999]},"runObject":{"FL-B18":[999,999,999,999,999],"FL-A18":[999,0,0,999]}},"FL-GABBY-69":{"id":"93357083","name":"FL-GABBY-69","colorObject":{"BEIGE":[999,999],"BLACK":[0],"WHITE":[999,999]},"runObject":{"FL-A18":[999,0,999],"FL-B18":[999,999]}},"FL-GRACEFUL-01":{"id":"93725227","name":"FL-GRACEFUL-01","colorObject":{"BLACK":[999,0],"RED":[999,999],"TAN":[999,999]},"runObject":{"FL-A18":[999,999,999],"FL-B18":[0,999,999]}},"FL-GRANDE-22":{"id":"92930480","name":"FL-GRANDE-22","colorObject":{"BEIGE PATENT":[0],"BLACK":[0,0],"CHARCOAL":[999,999],"NAVY":[999],"RED":[999,999],"TAUPE NUBUCK":[999,999],"WHITE":[999,999]},"runObject":{"FL-A18":[0,0,999,999,999,999,999],"FL-B18":[0,999,999,999,999]}},"FL-HANA-49":{"id":"93785438","name":"FL-HANA-49","colorObject":{"BEIGE":[0,999],"BLACK":[0,999],"LIGHT BLUE":[0,0],"LAVENDER":[0],"MAUVE":[999],"WHITE":[999]},"runObject":{"FL-A18":[0,0,0,0],"FL-B18":[999,999,0,999,999]}},"FL-HANA-49K":{"id":"93785439","name":"FL-HANA-49K","colorObject":{"BEIGE":[999],"BLACK":[0],"MAUVE":[0],"WHITE":[0]},"runObject":{"FL-E18":[999,0,0,0]}},"FL-ICEBERG-12":{"id":"94411632","name":"FL-ICEBERG-12","colorObject":{"RED":[0,0]},"runObject":{"FL-A18":[0],"FL-B18":[0]}},"FL-JALEN-88":{"id":"91777067","name":"FL-JALEN-88","colorObject":{"TAN":[999,0],"TAUPE":[999]},"runObject":{"FL-A18":[999,999],"FL-B18":[0]}},"FL-JOSINA-68":{"id":"92074309","name":"FL-JOSINA-68","colorObject":{"BLACK":[999,999],"CHAMPAGNE":[999,999],"SILVER":[999,999]},"runObject":{"FL-A18":[999,999,999],"FL-B18":[999,999,999]}},"FL-KALLY-2":{"id":"92143402","name":"FL-KALLY-2","colorObject":{"BLACK":[999],"CHAMPAGNE":[999]},"runObject":{"FL-A18":[999],"FL-B18":[999]}},"FL-KINSELLA-28K":{"id":"92143798","name":"FL-KINSELLA-28K","colorObject":{"BEIGE":[999],"BLACK":[999],"PINK":[999],"TAN":[999],"WHITE":[999]},"runObject":{"FL-E18":[999,999,999,999,999]}},"FL-KINSELLA-29K":{"id":"92143806","name":"FL-KINSELLA-29K","colorObject":{"BEIGE":[999],"BLACK":[999],"TAN":[999],"WHITE":[999]},"runObject":{"FL-E18":[999,999,999,999]}},"FL-KINSELLA-45K":{"id":"93009512","name":"FL-KINSELLA-45K","colorObject":{"BLACK":[999],"CHAMPAGNE":[999],"SILVER":[999],"TAUPE":[999]},"runObject":{"FL-E18":[999,999,999,999]}},"FL-KINSELLA-46K":{"id":"93009524","name":"FL-KINSELLA-46K","colorObject":{"CHAMPAGNE":[999],"SILVER":[999],"TAUPE":[999]},"runObject":{"FL-E18":[999,999,999]}},"FL-KINSELLA-49":{"id":"93009557","name":"FL-KINSELLA-49","colorObject":{"BLACK":[0],"CHAMPAGNE":[999,999],"ROSE GOLD":[999,999],"SILVER":[0],"TAUPE":[999,999],"WHITE":[999,999]},"runObject":{"FL-A18":[0,999,999,0,999,999],"FL-B18":[999,999,999,999]}},"FL-LAKOTA-38":{"id":"93126317","name":"FL-LAKOTA-38","colorObject":{"BLACK":[999,999],"GOLD":[999],"ROSE GOLD":[999,999,999],"SILVER":[999,999]},"runObject":{"FL-B18":[999,999,999,999],"FL-L18":[999,999,999],"FL-A18":[999]}},"FL-LEGOSA-11":{"id":"93013541","name":"FL-LEGOSA-11","colorObject":{"BLACK":[0],"BROWN":[999,999],"TAN":[999,999]},"runObject":{"FL-B18":[0,999,999],"FL-A18":[999,999]}},"FL-LIMITED-96":{"id":"93459485","name":"FL-LIMITED-96","colorObject":{"BLACK":[999],"CLEAR":[999,999],"NUDE":[999],"RED":[999]},"runObject":{"FL-A18":[999,999,999,999],"FL-B18":[999]}},"FL-LORIS-28":{"id":"92074317","name":"FL-LORIS-28","colorObject":{"BLACK NUBUCK":[0,999],"BLACK PATENT":[999],"TAUPE":[999]},"runObject":{"FL-A18":[0],"FL-B18":[999,999,999]}},"FL-LUG-07":{"id":"93965090","name":"FL-LUG-07","colorObject":{"BLACK":[999,0],"MULTI":[999,999],"RED":[999,999],"TIE DYE":[999,999]},"runObject":{"FL-A18":[999,999,999,999],"FL-B18":[0,999,999,999]}},"FL-MAGGIE-39":{"id":"91622697","name":"FL-MAGGIE-39","colorObject":{"BLACK":[999],"TAN":[999],"WHITE":[999]},"runObject":{"FL-A18":[999,999,999]}},"FL-MANGO-21":{"id":"91600441","name":"FL-MANGO-21","colorObject":{"BLACK":[0],"BROWN":[999,0],"TAN":[999,999]},"runObject":{"FL-A12":[0,999],"FL-B12":[0,999],"FL-L12":[999]}},"FL-MATCH-L8":{"id":"91683134","name":"FL-MATCH-L8","colorObject":{"BLACK":[999,0],"RED":[999,999],"TAN":[999,999],"TAUPE":[999,999]},"runObject":{"FL-A12":[999,999,999,999],"FL-B12":[0,999,999,999]}},"FL-MIKA-77":{"id":"93036077","name":"FL-MIKA-77","colorObject":{"TAUPE":[999,999],"WHITE":[999,0]},"runObject":{"FL-A18":[999,999],"FL-B18":[999,0]}},"FL-MILESTONE-10":{"id":"93353443","name":"FL-MILESTONE-10","colorObject":{"BLACK":[0]},"runObject":{"FL-A18":[0]}},"FL-NATALIE-33":{"id":"93668918","name":"FL-NATALIE-33","colorObject":{"BLACK":[999,999],"CHAMPAGNE":[999,0],"SILVER":[999]},"runObject":{"FL-A18":[999,999,999],"FL-B18":[999,0]}},"FL-NATALY-06":{"id":"91643200","name":"FL-NATALY-06","colorObject":{"ARGENT":[999,999],"BLACK NUBUCK":[999,999],"CHAMPAGNE":[999,999],"CHARCOAL":[999],"GOLD":[999],"LEOPARD":[999,999],"MUSTARD":[999],"PINK TIE DYE":[999],"REDNESS":[999],"ROYAL BLUE":[999],"SILVER":[999,999],"TAUPE":[999,999]},"runObject":{"FL-A18":[999,999,999,999,999,999,999,999,999],"FL-B18":[999,999,999,999,999,999,999,999,999]}},"FL-NATALY-06K":{"id":"92173965","name":"FL-NATALY-06K","colorObject":{"BLACK":[999],"CHAMPAGNE":[999],"SILVER":[999],"WHITE":[999]},"runObject":{"FL-E18":[999,999,999,999]}},"FL-NATALY-10":{"id":"91785792","name":"FL-NATALY-10","colorObject":{"CHAMPAGNE":[999,0],"SILVER":[999]},"runObject":{"FL-A18":[999,999],"FL-B18":[0]}},"FL-PERFORM-60":{"id":"93063694","name":"FL-PERFORM-60","colorObject":{"BLACK":[999,999],"CHAMPAGNE":[999,999],"SILVER":[999,999]},"runObject":{"FL-A18":[999,999,999],"FL-B18":[999,999,999]}},"FL-POPULAR-05":{"id":"92461498","name":"FL-POPULAR-05","colorObject":{"BLACK":[999,999],"BURGUNDY":[999,999],"TAN":[999,999],"TAUPE":[999,999]},"runObject":{"FL-A18":[999,999,999,999],"FL-B18":[999,999,999,999]}},"FL-QUALITY-83":{"id":"91741946","name":"FL-QUALITY-83","colorObject":{"BLACK":[999]},"runObject":{"FL-B18":[999]}},"FL-REFORM-2":{"id":"93114775","name":"FL-REFORM-2","colorObject":{"BLACK":[999,0],"RAINBOW":[999],"RED":[999,999],"TAN":[999,0],"TAUPE":[999]},"runObject":{"FL-A18":[999,999,999,999,999],"FL-B18":[0,999,0]}},"FL-REFORM-53KA":{"id":"92126162","name":"FL-REFORM-53KA","colorObject":{"BLACK":[999],"LIGHT PINK":[999],"RAINBOW":[999],"ROSE GOLD":[999],"TAN":[0]},"runObject":{"FL-DD":[999,999,999,999,0]}},"FL-REFORM-54":{"id":"91652699","name":"FL-REFORM-54","colorObject":{"BLACK":[999],"GOLD":[999,999],"MULTI":[999,999],"TAN":[999],"WHITE":[999,999]},"runObject":{"FL-B18":[999,999,999,999,999],"FL-A18":[999,999,999]}},"FL-REFORM-8":{"id":"91652732","name":"FL-REFORM-8","colorObject":{"BEIGE":[999,999],"BLACK":[999,999],"PINK":[999,999],"RED":[0,999],"TAN":[999,999],"WHITE":[999]},"runObject":{"FL-A18":[999,999,999,0,999,999],"FL-B18":[999,999,999,999,999]}},"FL-REGULAR-70K":{"id":"93944168","name":"FL-REGULAR-70K","colorObject":{"BLACK":[0],"PINK":[999],"TAUPE":[999]},"runObject":{"FL-E18":[0,999,999]}},"FL-REJOICE-04":{"id":"93487053","name":"FL-REJOICE-04","colorObject":{"BEIGE":[0]},"runObject":{"FL-B18":[0]}},"FL-RESUME-66":{"id":"92539809","name":"FL-RESUME-66","colorObject":{"BEIGE":[999,999],"BLACK":[999],"GOLD":[999,999],"LEOPARD":[999,999],"ROSE GOLD":[999,999],"TAN":[999,999],"WHITE":[999,0]},"runObject":{"FL-A18":[999,999,999,999,999,999],"FL-B18":[999,999,999,999,999,999,0]}},"FL-RILEY-74":{"id":"91653935","name":"FL-RILEY-74","colorObject":{"BLACK":[999,999],"BLUE PATENT":[999],"LEOPARD":[999,999],"RED":[999,999],"WHITE":[999,0]},"runObject":{"FL-A18":[999,999,999,999,999],"FL-B18":[999,999,999,0]}},"FL-ROAD-1":{"id":"93439432","name":"FL-ROAD-1","colorObject":{"BEIGE":[0]},"runObject":{"FL-A12":[0]}},"FL-ROYALTY-13":{"id":"94059952","name":"FL-ROYALTY-13","colorObject":{"BLACK":[999,0],"LIGHT BLUE":[999,999],"PINK":[999,999],"TAN":[999,999],"WHITE":[999]},"runObject":{"FL-A18":[999,999,999,999,999],"FL-B18":[0,999,999,999]}},"FL-SABINA-72K":{"id":"93070908","name":"FL-SABINA-72K","colorObject":{"BLACK":[999],"CHAMPAGNE":[999],"ROSE GOLD":[0],"SILVER":[999]},"runObject":{"FL-E18":[999,999,0,999]}},"FL-SAFETY-52":{"id":"93608466","name":"FL-SAFETY-52","colorObject":{"BLACK":[0,0],"BROWN":[999,999],"TAN":[999,999]},"runObject":{"FL-A18":[0,999,999],"FL-B18":[0,999,999]}},"FL-SATISFY-10":{"id":"93252190","name":"FL-SATISFY-10","colorObject":{"BLACK":[0,999],"WHITE":[999]},"runObject":{"FL-A18":[0,999],"FL-B18":[999]}},"FL-SCOBLE-48":{"id":"93070975","name":"FL-SCOBLE-48","colorObject":{"CHAMPAGNE":[999],"SILVER":[0]},"runObject":{"FL-B18":[999,0]}},"FL-SENSATIONAL-1":{"id":"91656774","name":"FL-SENSATIONAL-1","colorObject":{"BLACK":[999,999],"TAN":[999,999],"TAUPE":[999,999]},"runObject":{"FL-A18":[999,999,999],"FL-B18":[999,999,999]}},"FL-SIENNA-04":{"id":"91928019","name":"FL-SIENNA-04","colorObject":{"GOLD":[0,999],"SILVER":[999,999]},"runObject":{"FL-A18":[0,999],"FL-B18":[999,999]}},"FL-SIMILAR-08":{"id":"91848698","name":"FL-SIMILAR-08","colorObject":{"TAN":[0,999]},"runObject":{"FL-A18":[0],"FL-B18":[999]}},"FL-SONGFUL-1":{"id":"93071025","name":"FL-SONGFUL-1","colorObject":{"BLACK":[0,0],"CHAMPAGNE":[999,999],"SILVER":[999,999]},"runObject":{"FL-A18":[0,999,999],"FL-B18":[0,999,999]}},"FL-SONGFUL-6":{"id":"92089888","name":"FL-SONGFUL-6","colorObject":{"BLACK":[999],"CHAMPAGNE":[999,999],"CHARCOAL":[0,0],"PINK TIE DYE":[999,999],"RED":[999],"REDNESS":[999,999],"SILVER":[999,999],"TAN":[999,999],"WHITE":[999]},"runObject":{"FL-A18":[999,999,0,999,999,999,999,999,999],"FL-B18":[999,0,999,999,999,999]}},"FL-SUNRISE-39":{"id":"93075259","name":"FL-SUNRISE-39","colorObject":{"CHAMPAGNE":[999],"RED":[0,0],"SILVER":[0],"WHITE":[999,999]},"runObject":{"FL-A18":[999,0,0,999],"FL-B18":[0,999]}},"FL-SUPPORT-5":{"id":"91636409","name":"FL-SUPPORT-5","colorObject":{"BLACK":[999,0],"BROWN":[999],"TAUPE":[999]},"runObject":{"FL-A18":[999],"FL-B18":[0,999,999]}},"FL-UNIQUE-63":{"id":"93324767","name":"FL-UNIQUE-63","colorObject":{"BLACK":[999,999],"TAUPE":[999,999],"WHITE":[0,999]},"runObject":{"FL-A18":[999,999,0],"FL-B18":[999,999,999]}},"FL-UPGRADE-61K":{"id":"92218634","name":"FL-UPGRADE-61K","colorObject":{"TAN":[999]},"runObject":{"FL-E18":[999]}},"FL-YANLI-15":{"id":"93424404","name":"FL-YANLI-15","colorObject":{"BLACK":[999,999],"CAMEL":[999,999],"TAN":[999,999],"WHITE":[999,999]},"runObject":{"FL-A18":[999,999,999,999],"FL-B18":[999,999,999,999]}},"FL-YOUNG-02":{"id":"91815543","name":"FL-YOUNG-02","colorObject":{"BLACK":[0,0],"GOLD":[0],"RED PATENT":[999,999],"SILVER":[999],"TAUPE":[999],"WHITE":[999]},"runObject":{"FL-A18":[0,0,999,999,999,999],"FL-B18":[0,999]}},"FL-YULA-18":{"id":"94059963","name":"FL-YULA-18","colorObject":{"BLACK NUBUCK":[999,999],"NUDE NUBUCK":[999,999],"RED SUEDE":[999],"TAN":[999],"WHITE":[999]},"runObject":{"FL-A18":[999,999],"FL-B18":[999,999,999,999,999]}},"FL-YULA-32":{"id":"92176634","name":"FL-YULA-32","colorObject":{"ROSE GOLD":[999,0],"SILVER":[999,0]},"runObject":{"FL-A18":[999,999],"FL-B18":[0,0]}},"FL-ZANITA-19":{"id":"91679857","name":"FL-ZANITA-19","colorObject":{"BROWN":[0,0],"TAN":[0,0]},"runObject":{"FL-A12":[0,0],"FL-B12":[0,0]}}}